{
  "lr": "2026-04-14",
  "mi": "#1519",
  "m": "2026-04",
  "prs": [
    1529,
    1528,
    1526,
    1525,
    1524,
    1523,
    1521,
    1520,
    1518,
    1516,
    1515,
    1508,
    1502,
    1494,
    1493
  ],
  "c": 70,
  "cmts": [
    260,
    286,
    303,
    311,
    324,
    327,
    342,
    362,
    392,
    401,
    420,
    424,
    436,
    438,
    451,
    467,
    494,
    505,
    507,
    509,
    519,
    524,
    530,
    540,
    549,
    551,
    555,
    573,
    583,
    591,
    598,
    608,
    613,
    623,
    635,
    648,
    653,
    656,
    660,
    671,
    697,
    702,
    712,
    738,
    751,
    755,
    793,
    812,
    832,
    843,
    850,
    866,
    867,
    906,
    914,
    944,
    966,
    986,
    1010,
    1032,
    1057,
    1066,
    1097,
    1109,
    1159,
    1203,
    1227,
    1247,
    1259,
    1271,
    1322,
    1362,
    1381,
    1414,
    1437,
    1473,
    1475
  ],
  "n": "2026-04-14: Commented on #1247 (nuget script issue - recommended Microsoft.Data.SqlClient). PR #1529 all CI green (19/19). All open RA PRs pass CI. Monthly issue #1519 updated. PR #1493 (changelog v0.84.0) ready to merge. cmts list: added 1247. Checked CIs for #1526, #1518, #1515, #1529 - all passing.",
  "fix_attempts": {
    "692": {
      "pr": "repo-assist/fix-issue-692-remove-global-display-context",
      "pr_number": 1529,
      "status": "open",
      "date": "2026-04-13",
      "ci": "all_green"
    }
  }
}
